danbooru_scraper/__init__.py
danbooru_scraper/cli.py
danbooru_scraper/danbooru.py
danbooru_scraper-0.1.2.dist-info/LICENSE
danbooru_scraper-0.1.2.dist-info/METADATA
danbooru_scraper-0.1.2.dist-info/WHEEL
danbooru_scraper-0.1.2.dist-info/entry_points.txt
danbooru_scraper-0.1.2.dist-info/RECORD
